{
  "advancements:hidden/root": {
    "criteria": {
      "requirement": "2021-05-02 00:23:00 -0400"
    },
    "done": true
  },
  "game:inventory_changed": {
    "criteria": {
      "requirement": "2021-05-02 00:23:00 -0400"
    },
    "done": true
  },
  "advancements:root": {
    "criteria": {
      "requirement": "2021-05-02 00:23:00 -0400"
    },
    "done": true
  },
  "journal:root": {
    "criteria": {
      "requirement": "2021-05-02 00:23:00 -0400"
    },
    "done": true
  },
  "DataVersion": 2586
}