{"stats":{"minecraft:killed_by":{"minecraft:zombie":1},"minecraft:picked_up":{"minecraft:gold_nugget":22,"minecraft:potion":1,"minecraft:iron_nugget":49,"minecraft:emerald":1},"minecraft:custom":{"minecraft:time_since_rest":5216,"minecraft:crouch_one_cm":196,"minecraft:sprint_one_cm":75456,"minecraft:play_time":24204,"minecraft:deaths":7,"minecraft:damage_taken":1998,"minecraft:walk_one_cm":20507,"minecraft:sneak_time":194,"minecraft:drop":1,"minecraft:damage_dealt_resisted":4,"minecraft:jump":755,"minecraft:leave_game":3,"minecraft:walk_on_water_one_cm":565,"minecraft:time_since_death":5215,"minecraft:total_world_time":2173,"minecraft:damage_resisted":497,"minecraft:fall_one_cm":35396,"minecraft:fly_one_cm":247170},"minecraft:dropped":{"minecraft:knowledge_book":1},"minecraft:used":{"minecraft:bow":9,"minecraft:potion":1}},"DataVersion":3465}