{"stats":{"minecraft:dropped":{"minecraft:water_bucket":3,"minecraft:spruce_sign":1,"minecraft:clay":1,"minecraft:mooshroom_spawn_egg":1,"minecraft:crossbow":1002,"minecraft:barrier":3,"minecraft:cobblestone":1,"minecraft:knowledge_book":8,"minecraft:observer":1,"minecraft:leather":43,"minecraft:elytra":1,"minecraft:grass_block":1,"minecraft:emerald":1,"minecraft:flint":3,"minecraft:cyan_terracotta":3,"minecraft:acacia_sign":1,"minecraft:lava_bucket":1,"minecraft:dirt":1,"minecraft:packed_ice":1,"minecraft:wooden_axe":1,"minecraft:map":1,"minecraft:snowball":1,"minecraft:writable_book":1,"minecraft:blue_terracotta":1,"minecraft:zombie_spawn_egg":3,"minecraft:gray_stained_glass":1,"minecraft:green_terracotta":1,"minecraft:player_head":14,"minecraft:ender_chest":103,"minecraft:blue_wool":1,"minecraft:obsidian":1,"minecraft:black_terracotta":1,"minecraft:stone_slab":1,"minecraft:dolphin_spawn_egg":1,"minecraft:white_terracotta":1,"minecraft:oak_sign":9,"minecraft:filled_map":3,"minecraft:cyan_wool":1,"minecraft:tipped_arrow":670,"minecraft:stone":3,"minecraft:sea_pickle":1,"minecraft:trident":1,"minecraft:blue_ice":1,"minecraft:cat_spawn_egg":329,"minecraft:leather_leggings":1,"minecraft:birch_sign":12,"minecraft:painting":1,"minecraft:polished_granite":1},"minecraft:picked_up":{"minecraft:ender_chest":6,"minecraft:leather_leggings":1,"minecraft:potion":8,"minecraft:elytra":1,"minecraft:oak_sign":1,"minecraft:gold_nugget":1882,"minecraft:red_dye":1,"minecraft:player_head":9,"minecraft:iron_nugget":4818,"minecraft:tipped_arrow":1,"minecraft:orange_dye":1,"minecraft:stone":104,"minecraft:red_shulker_box":1,"minecraft:purple_dye":2,"minecraft:water_bucket":1,"minecraft:yellow_dye":2,"minecraft:filled_map":1,"minecraft:light_blue_dye":1,"minecraft:cobweb":94,"minecraft:leather_helmet":2,"minecraft:diamond":3,"minecraft:writable_book":3,"minecraft:crossbow":6,"minecraft:birch_sign":1,"minecraft:emerald":193},"minecraft:killed":{"minecraft:vindicator":1,"minecraft:dolphin":1,"minecraft:slime":9,"minecraft:guardian":2,"minecraft:illusioner":1,"minecraft:bat":2,"minecraft:polar_bear":20,"minecraft:pillager":1,"minecraft:zombie":12,"minecraft:mooshroom":9},"minecraft:custom":{"minecraft:mob_kills":1426,"minecraft:open_barrel":15,"minecraft:open_shulker_box":11,"minecraft:bell_ring":8,"minecraft:damage_dealt_resisted":6361431,"minecraft:eat_cake_slice":2,"minecraft:leave_game":187,"minecraft:time_since_death":11994,"minecraft:climb_one_cm":195048,"minecraft:damage_resisted":3846426,"minecraft:sprint_one_cm":13090842,"minecraft:walk_one_cm":3688988,"minecraft:drop":2243,"minecraft:play_time":9808728,"minecraft:deaths":244,"minecraft:sneak_time":134801,"minecraft:walk_under_water_one_cm":167529,"minecraft:interact_with_lectern":17,"minecraft:jump":109318,"minecraft:walk_on_water_one_cm":347092,"minecraft:total_world_time":8712,"minecraft:interact_with_cartography_table":2,"minecraft:interact_with_loom":8,"minecraft:interact_with_stonecutter":1,"minecraft:time_since_rest":11997,"minecraft:damage_taken":54165,"minecraft:open_enderchest":12,"minecraft:damage_dealt":12945,"minecraft:interact_with_beacon":1,"minecraft:swim_one_cm":227823,"minecraft:fly_one_cm":77484038,"minecraft:player_kills":13,"minecraft:open_chest":5,"minecraft:crouch_one_cm":135532,"minecraft:aviate_one_cm":30715158,"minecraft:fall_one_cm":2276098,"minecraft:inspect_dispenser":1},"minecraft:used":{"minecraft:oak_trapdoor":1,"minecraft:netherite_sword":164,"minecraft:trident":78,"minecraft:orange_concrete_powder":4,"minecraft:jungle_leaves":171,"minecraft:blue_terracotta":53,"minecraft:rose_bush":1,"minecraft:writable_book":4,"minecraft:polished_granite_stairs":5,"minecraft:dead_tube_coral_block":80,"minecraft:smooth_quartz_slab":15,"minecraft:red_concrete":16,"minecraft:stone_shovel":1,"minecraft:spruce_slab":6,"minecraft:redstone":13,"minecraft:ladder":4,"minecraft:oak_sign":150,"minecraft:mycelium":21,"minecraft:light_blue_terracotta":1,"minecraft:stripped_warped_stem":9,"minecraft:spruce_planks":55,"minecraft:white_terracotta":17,"minecraft:ender_chest":1,"minecraft:stone":588,"minecraft:zombie_spawn_egg":98,"minecraft:green_terracotta":116,"minecraft:quartz_stairs":6,"minecraft:farmland":1,"minecraft:player_head":14,"minecraft:netherrack":21,"minecraft:debug_stick":2,"minecraft:orange_stained_glass":96,"minecraft:mooshroom_spawn_egg":4,"minecraft:dirt":11,"minecraft:warped_wart_block":22,"minecraft:skeleton_spawn_egg":1,"minecraft:crimson_hyphae":158,"minecraft:prismarine_bricks":73,"minecraft:spruce_stairs":2,"minecraft:carrot":1,"minecraft:bee_nest":1,"minecraft:oak_wood":267,"minecraft:polished_granite_slab":5,"minecraft:granite":5,"minecraft:cyan_wool":42,"minecraft:snowball":1197,"minecraft:dark_oak_planks":1,"minecraft:red_shulker_box":1,"minecraft:obsidian":9,"minecraft:red_sandstone_stairs":2,"minecraft:mossy_cobblestone_stairs":6,"minecraft:wooden_axe":9,"minecraft:glass":1491,"minecraft:packed_ice":19,"minecraft:honey_block":351,"minecraft:cyan_terracotta":33,"minecraft:villager_spawn_egg":2,"minecraft:quartz_pillar":14,"minecraft:cyan_shulker_box":35,"minecraft:yellow_stained_glass":28,"minecraft:red_wool":14,"minecraft:spruce_wood":2,"minecraft:lantern":7,"minecraft:grass_block":18,"minecraft:oak_stairs":2,"minecraft:slime_block":16,"minecraft:polished_andesite_stairs":19,"minecraft:warped_nylium":5,"minecraft:chicken_spawn_egg":8,"minecraft:dark_oak_wood":2,"minecraft:dark_oak_slab":21,"minecraft:polished_blackstone_brick_stairs":9,"minecraft:mossy_cobblestone_slab":42,"minecraft:crimson_planks":10,"minecraft:prismarine_slab":7,"minecraft:stone_brick_stairs":57,"minecraft:stone_bricks":124,"minecraft:repeater":4,"minecraft:honeycomb_block":2853,"minecraft:glowstone":54,"minecraft:dolphin_spawn_egg":31,"minecraft:red_carpet":1,"minecraft:redstone_lamp":6,"minecraft:lime_concrete":6,"minecraft:hay_block":3,"minecraft:magenta_terracotta":4,"minecraft:lime_stained_glass":2,"minecraft:cyan_concrete_powder":10,"minecraft:observer":7,"minecraft:lime_glazed_terracotta":21,"minecraft:knowledge_book":44,"minecraft:wheat_seeds":4,"minecraft:water_bucket":190,"minecraft:dark_oak_stairs":5,"minecraft:mossy_stone_bricks":72,"minecraft:warped_stem":17,"minecraft:diorite":2,"minecraft:cow_spawn_egg":1,"minecraft:cobblestone_stairs":2,"minecraft:dirt_path":2,"minecraft:prismarine_brick_slab":2,"minecraft:snow_block":32,"minecraft:polished_andesite":73,"minecraft:lime_wool":3,"minecraft:oak_planks":11,"minecraft:cartography_table":1,"minecraft:blue_wool":37,"minecraft:andesite_slab":60,"minecraft:lime_concrete_powder":9,"minecraft:mossy_stone_brick_stairs":47,"minecraft:black_shulker_box":6,"minecraft:spruce_sign":1,"minecraft:stonecutter":3,"minecraft:clay":1,"minecraft:cobblestone_slab":14,"minecraft:cracked_stone_bricks":80,"minecraft:polished_blackstone_bricks":266,"minecraft:oak_leaves":116,"minecraft:mossy_cobblestone":66,"minecraft:sand":5,"minecraft:blast_furnace":1,"minecraft:vine":98,"minecraft:yellow_terracotta":26,"minecraft:cyan_glazed_terracotta":1,"minecraft:dark_prismarine_slab":6,"minecraft:tnt":2,"minecraft:loom":3,"minecraft:yellow_concrete":25,"minecraft:light_blue_wool":49,"minecraft:crossbow":5340,"minecraft:birch_sign":217,"minecraft:smooth_red_sandstone":5,"minecraft:blue_ice":8,"minecraft:polar_bear_spawn_egg":5,"minecraft:gray_concrete":4,"minecraft:shulker_spawn_egg":2,"minecraft:painting":1,"minecraft:smooth_red_sandstone_stairs":1,"minecraft:spruce_log":18,"minecraft:warped_planks":42,"minecraft:dark_oak_door":4,"minecraft:mushroom_stem":29,"minecraft:redstone_torch":5,"minecraft:blue_glazed_terracotta":19,"minecraft:enderman_spawn_egg":1,"minecraft:black_terracotta":6,"minecraft:wooden_hoe":1,"minecraft:gray_terracotta":1,"minecraft:dark_prismarine":37,"minecraft:lever":25,"minecraft:green_concrete":30,"minecraft:black_concrete":1,"minecraft:firework_rocket":414,"minecraft:acacia_sign":2,"minecraft:gray_shulker_box":12,"minecraft:command_block":120,"minecraft:light_gray_concrete":2,"minecraft:cracked_polished_blackstone_bricks":63,"minecraft:barrier":464,"minecraft:map":8,"minecraft:stone_button":13,"minecraft:lectern":19,"minecraft:cyan_concrete":10,"minecraft:stone_slab":616,"minecraft:red_terracotta":20,"minecraft:polished_granite":20,"minecraft:crimson_nylium":44,"minecraft:cat_spawn_egg":1,"minecraft:polished_andesite_slab":4,"minecraft:soul_lantern":16,"minecraft:yellow_wool":1,"minecraft:crimson_sign":6,"minecraft:stripped_warped_hyphae":15,"minecraft:nether_wart_block":17,"minecraft:smooth_red_sandstone_slab":3,"minecraft:wooden_sword":1,"minecraft:cobblestone":1,"minecraft:potion":23,"minecraft:andesite":128,"minecraft:dark_oak_fence":93,"minecraft:andesite_stairs":6,"minecraft:lapis_block":12,"minecraft:green_concrete_powder":2,"minecraft:chain_command_block":26,"minecraft:repeating_command_block":34,"minecraft:smooth_stone_slab":4,"minecraft:ice":110,"minecraft:white_concrete":54,"minecraft:coarse_dirt":27,"minecraft:brown_mushroom_block":1,"minecraft:smooth_stone":57,"minecraft:splash_potion":307,"minecraft:pillager_spawn_egg":1,"minecraft:gray_stained_glass":145},"minecraft:killed_by":{"minecraft:player":110,"minecraft:polar_bear":1,"minecraft:spider":3,"minecraft:iron_golem":3,"minecraft:skeleton":4,"minecraft:guardian":1,"minecraft:zombie":23,"minecraft:vex":1,"minecraft:illusioner":2}},"DataVersion":2975}