{"stats":{"minecraft:killed_by":{"minecraft:zombified_piglin":1,"minecraft:wither_skeleton":2,"minecraft:piglin_brute":1,"minecraft:creeper":2,"minecraft:polar_bear":1,"minecraft:pillager":1,"minecraft:drowned":1,"minecraft:piglin":2,"minecraft:zombie":31,"minecraft:vex":1,"minecraft:illusioner":2,"minecraft:player":110,"minecraft:spider":3,"minecraft:iron_golem":3,"minecraft:skeleton":4,"minecraft:guardian":1},"minecraft:custom":{"minecraft:interact_with_crafting_table":1,"minecraft:open_barrel":29,"minecraft:open_shulker_box":11,"minecraft:bell_ring":8,"minecraft:eat_cake_slice":2,"minecraft:leave_game":237,"minecraft:time_since_death":707440,"minecraft:damage_resisted":23857384,"minecraft:sprint_one_cm":20648664,"minecraft:drop":4932,"minecraft:talked_to_villager":1,"minecraft:play_time":13382002,"minecraft:deaths":274,"minecraft:jump":153995,"minecraft:walk_on_water_one_cm":409626,"minecraft:interact_with_cartography_table":2,"minecraft:interact_with_loom":8,"minecraft:open_enderchest":29,"minecraft:damage_dealt":14949,"minecraft:interact_with_beacon":1,"minecraft:player_kills":16,"minecraft:crouch_one_cm":165979,"minecraft:inspect_dispenser":1,"minecraft:horse_one_cm":1082,"minecraft:mob_kills":2860,"minecraft:damage_dealt_resisted":12990282,"minecraft:climb_one_cm":362545,"minecraft:walk_one_cm":5335663,"minecraft:sneak_time":163784,"minecraft:walk_under_water_one_cm":253318,"minecraft:interact_with_lectern":19,"minecraft:total_world_time":3580007,"minecraft:interact_with_stonecutter":1,"minecraft:time_since_rest":707441,"minecraft:damage_taken":70314,"minecraft:damage_absorbed":440,"minecraft:swim_one_cm":257346,"minecraft:fly_one_cm":103680881,"minecraft:open_chest":14,"minecraft:aviate_one_cm":31445073,"minecraft:fall_one_cm":6757874},"minecraft:dropped":{"minecraft:spruce_sign":1,"minecraft:clay":1,"minecraft:mule_spawn_egg":2,"minecraft:crossbow":1961,"minecraft:leather":65,"minecraft:elytra":1,"minecraft:flint":4,"minecraft:emerald":1,"minecraft:cyan_terracotta":3,"minecraft:dirt":1,"minecraft:packed_ice":1,"minecraft:ice":3,"minecraft:mangrove_stairs":1,"minecraft:snowball":1,"minecraft:writable_book":1,"minecraft:phantom_membrane":1,"minecraft:chiseled_polished_blackstone":1,"minecraft:compass":4,"minecraft:blue_wool":1,"minecraft:obsidian":1,"minecraft:black_terracotta":1,"minecraft:oak_planks":2,"minecraft:tipped_arrow":2259,"minecraft:trident":1,"minecraft:leather_leggings":1,"minecraft:painting":1,"minecraft:polished_granite":1,"minecraft:netherrack":2,"minecraft:water_bucket":3,"minecraft:mooshroom_spawn_egg":1,"minecraft:tnt":6,"minecraft:barrier":3,"minecraft:cobblestone":1,"minecraft:knowledge_book":95,"minecraft:observer":1,"minecraft:command_block":1,"minecraft:grass_block":1,"minecraft:acacia_sign":1,"minecraft:lava_bucket":1,"minecraft:wooden_axe":1,"minecraft:map":1,"minecraft:zombie_head":1,"minecraft:blue_glazed_terracotta":1,"minecraft:polished_basalt":1,"minecraft:blue_terracotta":1,"minecraft:zombie_spawn_egg":3,"minecraft:gray_stained_glass":1,"minecraft:green_terracotta":1,"minecraft:player_head":15,"minecraft:ender_chest":103,"minecraft:stone_slab":1,"minecraft:dolphin_spawn_egg":1,"minecraft:white_terracotta":1,"minecraft:oak_sign":9,"minecraft:filled_map":3,"minecraft:cyan_wool":1,"minecraft:stone":3,"minecraft:sea_pickle":1,"minecraft:blue_ice":1,"minecraft:cat_spawn_egg":329,"minecraft:birch_sign":12,"minecraft:globe_banner_pattern":4},"minecraft:crafted":{"minecraft:leather_chestplate":1},"minecraft:mined":{"minecraft:tnt":2},"minecraft:picked_up":{"minecraft:ender_chest":6,"minecraft:potion":9,"minecraft:globe_banner_pattern":4,"minecraft:oak_sign":1,"minecraft:gold_nugget":5643,"minecraft:red_dye":26,"minecraft:tipped_arrow":3,"minecraft:mangrove_stairs":1,"minecraft:polished_basalt":1,"minecraft:mangrove_roots":1,"minecraft:water_bucket":1,"minecraft:light_blue_dye":70,"minecraft:diamond":3,"minecraft:writable_book":3,"minecraft:crossbow":6,"minecraft:emerald":930,"minecraft:netherrack":1,"minecraft:leather_leggings":1,"minecraft:elytra":1,"minecraft:player_head":9,"minecraft:iron_nugget":10167,"minecraft:mule_spawn_egg":1,"minecraft:egg":2,"minecraft:orange_dye":22,"minecraft:stone":104,"minecraft:red_shulker_box":1,"minecraft:purple_dye":35,"minecraft:tripwire_hook":8,"minecraft:yellow_dye":35,"minecraft:filled_map":1,"minecraft:cobweb":94,"minecraft:leather_helmet":2,"minecraft:lime_dye":1,"minecraft:birch_sign":1},"minecraft:killed":{"minecraft:zombified_piglin":1,"minecraft:dolphin":1,"minecraft:guardian":2,"minecraft:illusioner":1,"minecraft:magma_cube":7,"minecraft:zombie":14,"minecraft:mooshroom":9,"minecraft:ghast":1,"minecraft:vindicator":1,"minecraft:slime":9,"minecraft:snow_golem":1,"minecraft:bat":2,"minecraft:wandering_trader":1,"minecraft:polar_bear":20,"minecraft:wither_skeleton":1},"minecraft:used":{"minecraft:moss_block":4,"minecraft:blue_terracotta":53,"minecraft:writable_book":4,"minecraft:polished_granite_stairs":5,"minecraft:light_gray_dye":1,"minecraft:polished_deepslate":2,"minecraft:smooth_quartz_slab":19,"minecraft:spruce_slab":6,"minecraft:dispenser":4,"minecraft:elytra":1,"minecraft:ladder":10,"minecraft:mangrove_fence_gate":7,"minecraft:oak_sign":150,"minecraft:white_terracotta":23,"minecraft:stone":596,"minecraft:zombie_spawn_egg":105,"minecraft:quartz_stairs":6,"minecraft:player_head":18,"minecraft:farmland":1,"minecraft:green_terracotta":123,"minecraft:debug_stick":18,"minecraft:mooshroom_spawn_egg":4,"minecraft:skeleton_spawn_egg":1,"minecraft:carrot":1,"minecraft:deepslate_tile_slab":24,"minecraft:cracked_deepslate_tiles":4,"minecraft:tuff":63,"minecraft:cyan_wool":42,"minecraft:snowball":1197,"minecraft:obsidian":10,"minecraft:big_dripleaf":12,"minecraft:red_sandstone_stairs":2,"minecraft:glass":1491,"minecraft:honey_block":351,"minecraft:packed_ice":90,"minecraft:cyan_terracotta":38,"minecraft:mangrove_log":27,"minecraft:stripped_dark_oak_wood":1,"minecraft:villager_spawn_egg":2,"minecraft:quartz_pillar":14,"minecraft:mangrove_stairs":68,"minecraft:red_wool":14,"minecraft:spruce_wood":3,"minecraft:lantern":7,"minecraft:grass_block":25,"minecraft:polished_andesite_stairs":19,"minecraft:packed_mud":5,"minecraft:warped_nylium":6,"minecraft:dark_oak_wood":2,"minecraft:dark_oak_slab":21,"minecraft:mossy_cobblestone_slab":42,"minecraft:stone_brick_stairs":57,"minecraft:stone_bricks":124,"minecraft:stripped_mangrove_log":23,"minecraft:dolphin_spawn_egg":31,"minecraft:red_carpet":1,"minecraft:repeater":4,"minecraft:redstone_lamp":6,"minecraft:honeycomb_block":2853,"minecraft:bow":57,"minecraft:hay_block":3,"minecraft:mangrove_roots":120,"minecraft:mangrove_slab":159,"minecraft:pearlescent_froglight":26,"minecraft:dark_prismarine_stairs":13,"minecraft:lime_glazed_terracotta":21,"minecraft:mangrove_leaves":78,"minecraft:dark_oak_stairs":5,"minecraft:mossy_stone_bricks":72,"minecraft:diorite":2,"minecraft:cow_spawn_egg":1,"minecraft:red_stained_glass":11,"minecraft:prismarine":1,"minecraft:oak_planks":11,"minecraft:blackstone":6,"minecraft:lime_concrete_powder":9,"minecraft:leather_chestplate":1,"minecraft:mossy_stone_brick_stairs":47,"minecraft:clay":1,"minecraft:oak_leaves":116,"minecraft:smooth_quartz_stairs":9,"minecraft:sand":5,"minecraft:yellow_terracotta":26,"minecraft:loom":3,"minecraft:light_blue_wool":49,"minecraft:smooth_red_sandstone":5,"minecraft:blast_furnace":1,"minecraft:crossbow":9987,"minecraft:yellow_concrete":25,"minecraft:blue_ice":32,"minecraft:dripstone_block":1,"minecraft:ochre_froglight":33,"minecraft:shulker_spawn_egg":2,"minecraft:gray_concrete":8,"minecraft:deepslate_brick_stairs":10,"minecraft:lightning_rod":1,"minecraft:redstone_torch":5,"minecraft:black_terracotta":6,"minecraft:enderman_spawn_egg":1,"minecraft:lever":25,"minecraft:green_concrete":30,"minecraft:blue_glazed_terracotta":19,"minecraft:hoglin_spawn_egg":5,"minecraft:black_concrete":79,"minecraft:firework_rocket":688,"minecraft:gray_shulker_box":12,"minecraft:light_gray_concrete":2,"minecraft:barrier":505,"minecraft:stone_button":14,"minecraft:verdant_froglight":25,"minecraft:lectern":19,"minecraft:red_terracotta":20,"minecraft:polished_granite":20,"minecraft:deepslate":46,"minecraft:cat_spawn_egg":1,"minecraft:polished_andesite_slab":4,"minecraft:soul_lantern":16,"minecraft:stripped_warped_hyphae":15,"minecraft:nether_wart_block":17,"minecraft:smooth_red_sandstone_slab":3,"minecraft:wooden_sword":1,"minecraft:dark_oak_fence":93,"minecraft:chain":16,"minecraft:green_concrete_powder":2,"minecraft:andesite":166,"minecraft:piglin_spawn_egg":9,"minecraft:smooth_stone_slab":4,"minecraft:ice":116,"minecraft:white_concrete":54,"minecraft:coarse_dirt":27,"minecraft:gray_stained_glass":145,"minecraft:oak_trapdoor":1,"minecraft:orange_concrete_powder":4,"minecraft:trident":78,"minecraft:netherite_sword":179,"minecraft:jungle_leaves":171,"minecraft:rose_bush":1,"minecraft:iron_bars":2,"minecraft:dead_tube_coral_block":85,"minecraft:flint_and_steel":3,"minecraft:dead_bush":14,"minecraft:red_concrete":16,"minecraft:stone_shovel":1,"minecraft:redstone":13,"minecraft:light_blue_terracotta":1,"minecraft:mycelium":21,"minecraft:stripped_warped_stem":9,"minecraft:spruce_planks":55,"minecraft:ender_chest":1,"minecraft:mangrove_fence":4,"minecraft:structure_block":1,"minecraft:netherrack":119,"minecraft:orange_stained_glass":96,"minecraft:dirt":22,"minecraft:warped_wart_block":22,"minecraft:prismarine_bricks":73,"minecraft:spruce_stairs":2,"minecraft:twisting_vines":5,"minecraft:crimson_hyphae":159,"minecraft:oak_wood":267,"minecraft:bee_nest":1,"minecraft:polished_granite_slab":5,"minecraft:glow_lichen":20,"minecraft:granite":5,"minecraft:small_dripleaf":24,"minecraft:mossy_cobblestone_stairs":6,"minecraft:dark_oak_planks":1,"minecraft:red_shulker_box":1,"minecraft:wooden_axe":9,"minecraft:cyan_shulker_box":35,"minecraft:yellow_stained_glass":32,"minecraft:muddy_mangrove_roots":50,"minecraft:oak_stairs":2,"minecraft:rooted_dirt":3,"minecraft:slime_block":18,"minecraft:smooth_sandstone":41,"minecraft:chicken_spawn_egg":8,"minecraft:polished_blackstone_brick_stairs":9,"minecraft:smooth_quartz":1,"minecraft:piglin_brute_spawn_egg":1,"minecraft:crimson_planks":10,"minecraft:prismarine_slab":7,"minecraft:basalt":12,"minecraft:glowstone":55,"minecraft:lime_concrete":6,"minecraft:gray_glazed_terracotta":4,"minecraft:magenta_terracotta":4,"minecraft:lime_stained_glass":7,"minecraft:deepslate_tile_stairs":8,"minecraft:drowned_spawn_egg":1,"minecraft:acacia_wood":1,"minecraft:cyan_concrete_powder":10,"minecraft:cobbled_deepslate":5,"minecraft:observer":7,"minecraft:knowledge_book":54,"minecraft:wheat_seeds":4,"minecraft:water_bucket":378,"minecraft:warped_stem":17,"minecraft:mangrove_wood":45,"minecraft:dirt_path":2,"minecraft:cobblestone_stairs":2,"minecraft:prismarine_brick_slab":42,"minecraft:snow_block":32,"minecraft:polished_andesite":73,"minecraft:lime_wool":5,"minecraft:cartography_table":1,"minecraft:blue_wool":37,"minecraft:andesite_slab":60,"minecraft:black_shulker_box":6,"minecraft:spruce_sign":2,"minecraft:stonecutter":3,"minecraft:glow_ink_sac":1,"minecraft:cobblestone_slab":14,"minecraft:polished_blackstone_bricks":266,"minecraft:cracked_stone_bricks":80,"minecraft:mossy_cobblestone":66,"minecraft:diamond_block":16,"minecraft:mangrove_trapdoor":107,"minecraft:vine":122,"minecraft:crafting_table":1,"minecraft:tnt":2,"minecraft:dark_prismarine_slab":37,"minecraft:cyan_glazed_terracotta":1,"minecraft:crimson_trapdoor":15,"minecraft:birch_sign":226,"minecraft:campfire":11,"minecraft:polar_bear_spawn_egg":5,"minecraft:painting":1,"minecraft:mangrove_sign":4,"minecraft:smooth_red_sandstone_stairs":1,"minecraft:warped_planks":42,"minecraft:spruce_log":18,"minecraft:dark_oak_door":4,"minecraft:mushroom_stem":29,"minecraft:gray_terracotta":1,"minecraft:mud":417,"minecraft:netherite_block":12,"minecraft:dark_prismarine":37,"minecraft:wooden_hoe":1,"minecraft:acacia_sign":2,"minecraft:command_block":161,"minecraft:cracked_polished_blackstone_bricks":63,"minecraft:map":8,"minecraft:cyan_concrete":10,"minecraft:stone_slab":616,"minecraft:crimson_nylium":44,"minecraft:yellow_wool":1,"minecraft:crimson_sign":6,"minecraft:cobblestone":8,"minecraft:potion":51,"minecraft:lapis_block":12,"minecraft:sandstone_slab":15,"minecraft:andesite_stairs":6,"minecraft:chain_command_block":26,"minecraft:repeating_command_block":34,"minecraft:sea_pickle":13,"minecraft:kelp":5,"minecraft:brown_mushroom_block":1,"minecraft:smooth_stone":57,"minecraft:splash_potion":308,"minecraft:pillager_spawn_egg":1}},"DataVersion":3218}